<Properties StartupConfiguration="{85884340-90B6-40B7-B4D6-7778FE7F66F5}|Default">
  <MonoDevelop.Ide.Workbench ActiveDocument="BusinessLayer/InitRoles.cs">
    <Files>
      <File FileName="Cmagru42/Controllers/AccountController.cs" Line="473" Column="35" />
      <File FileName="Cmagru42/Models/PhotoWallViewModels/GetImgOwnerPermissionsViewModel.cs" Line="1" Column="1" />
      <File FileName="Cmagru42/Controllers/PhotoWallController.cs" Line="165" Column="13" />
      <File FileName="Cmagru42/Views/PhotoWall/_DetailedImgDispPartial.cshtml" Line="1" Column="1" />
      <File FileName="Cmagru42/wwwroot/js/DetailedImgViewer.js" Line="40" Column="40" />
      <File FileName="Cmagru42/Startup.cs" Line="1" Column="1" />
      <File FileName="BusinessLayer/UserUtils.cs" Line="1" Column="1" />
      <File FileName="BusinessLayer/InitRoles.cs" Line="34" Column="13" />
    </Files>
  </MonoDevelop.Ide.Workbench>
  <MonoDevelop.Ide.Workspace ActiveConfiguration="Debug" />
  <MonoDevelop.Ide.DebuggingService.Breakpoints>
    <BreakpointStore />
  </MonoDevelop.Ide.DebuggingService.Breakpoints>
  <MonoDevelop.Ide.DebuggingService.PinnedWatches />
  <MultiItemStartupConfigurations />
  <MonoDevelop.Ide.ItemProperties.Presentation PreferredExecutionTarget="MonoDevelop.Default" />
</Properties>